helloworld.py
morris_helloworld-0.1.dist-info/LICENSE.txt
morris_helloworld-0.1.dist-info/METADATA
morris_helloworld-0.1.dist-info/WHEEL
morris_helloworld-0.1.dist-info/top_level.txt
morris_helloworld-0.1.dist-info/RECORD
