Metadata-Version: 2.1
Name: morris-helloworld
Version: 0.1
Summary: Say Hello by Morris !
Home-page: UNKNOWN
Author: Morris Lee
Author-email: info.leekahwin@gmail.com
License: UNKNOWN
Platform: UNKNOWN
Classifier: Programming Language :: Python :: 3
Classifier: Programming Language :: Python :: 3.6
Classifier: Programming Language :: Python :: 3.7
Classifier: License :: OSI Approved :: GNU General Public License v2 or later (GPLv2+)
Classifier: Operating System :: OS Independent
